rebel/__init__.py
rebel/aggregator/__init__.py
rebel/aggregator/aggregator.py
rebel/cli.py
rebel/collector/__init__.py
rebel/collector/api_client.py
rebel/collector/collector.py
rebel/collector/openai_api_client.py
rebel/deepeval/__init__.py
rebel/deepeval/client.py
rebel/deepeval/metric.py
rebel/evaluator/__init__.py
rebel/evaluator/evaluator.py
rebel/extractor/__init__.py
rebel/extractor/extractor.py
rebel/extractor/test_case_registry.py
rebel/metrics/__init__.py
rebel/metrics/contextual_f_score.py
rebel/metrics/tool_calls_accuracy.py
rebel/models/__init__.py
rebel/models/api.py
rebel/models/evaluation.py
rebel/models/extraction.py
rebel/models/metric.py
rebel/models/test.py
rebel/saver/__init__.py
rebel/saver/saver.py
rebel/utils/__init__.py
rebel/utils/openai_client.py
rebel/workflow.py
rebel_eval-1.1.1.dist-info/LICENSE
rebel_eval-1.1.1.dist-info/METADATA
rebel_eval-1.1.1.dist-info/WHEEL
rebel_eval-1.1.1.dist-info/entry_points.txt
rebel_eval-1.1.1.dist-info/RECORD
