Metadata-Version: 2.1
Name: rebel-eval
Version: 1.1.1
Summary: RAG Evaluation Benchmark and Evaluation Library
Author: Alexander Ploskin
Author-email: ploskin0107@gmail.com
Requires-Python: >=3.12,<4.0
Classifier: Programming Language :: Python :: 3
Classifier: Programming Language :: Python :: 3.12
Provides-Extra: deepeval
Requires-Dist: deepeval (>=2.6.4,<3.0.0) ; extra == "deepeval"
Requires-Dist: instructor (>=1.9.0,<2.0.0)
Requires-Dist: joblib (>=1.5.1,<2.0.0)
Requires-Dist: numpy (>=2.3.1,<3.0.0)
Requires-Dist: openai (>=1.93.0,<2.0.0)
Requires-Dist: pydantic (>=2.11.7,<3.0.0)
Requires-Dist: scikit-learn (>=1.7.0,<2.0.0)
